xsl/__init__.py
xsl/__main__.py
xsl/cli.py
xsl/editor.py
xsl/server.py
xsl/utils.py
xsl-0.1.9.dist-info/LICENSE
xsl-0.1.9.dist-info/METADATA
xsl-0.1.9.dist-info/WHEEL
xsl-0.1.9.dist-info/entry_points.txt
xsl-0.1.9.dist-info/RECORD
