Metadata-Version: 2.3
Name: xsl
Version: 0.1.9
Summary: Universal File Editor for XML/SVG/HTML with XPath and CSS selector support
License: Apache-2.0
Keywords: xml,svg,html,xpath,editor,cli
Author: Tom Sapletta
Author-email: info@softreck.dev
Requires-Python: >=3.8.1,<4.0
Classifier: Development Status :: 4 - Beta
Classifier: Intended Audience :: Developers
Classifier: License :: OSI Approved :: Apache Software License
Classifier: Programming Language :: Python :: 3
Classifier: Programming Language :: Python :: 3.9
Classifier: Programming Language :: Python :: 3.10
Classifier: Programming Language :: Python :: 3.11
Classifier: Programming Language :: Python :: 3.12
Classifier: Programming Language :: Python :: 3.13
Classifier: Programming Language :: Python :: 3.8
Classifier: Topic :: Software Development :: Libraries :: Python Modules
Classifier: Topic :: Text Processing :: Markup :: HTML
Classifier: Topic :: Text Processing :: Markup :: XML
Provides-Extra: css
Provides-Extra: full
Provides-Extra: remote
Provides-Extra: xpath
Requires-Dist: beautifulsoup4 (>=4.11.0,<5.0.0) ; extra == "full" or extra == "css"
Requires-Dist: lxml (>=4.9.0,<5.0.0) ; extra == "full" or extra == "xpath"
Requires-Dist: requests (>=2.28.0,<3.0.0) ; extra == "full" or extra == "remote"
Project-URL: Documentation, https://github.com/veridock/xsl/docs
Project-URL: Homepage, https://github.com/veridock/xsl
Project-URL: Repository, https://github.com/veridock/xsl
